uif_server/.__main__.py.un~
uif_server/.caddy_server.txt.un~
uif_server/.test_uif_server.py.un~
uif_server/.uif_server.py.un~
uif_server/__init__.py
uif_server/__main__.py
uif_server/__main__.py~
uif_server/caddy_server.txt
uif_server/caddy_server.txt~
uif_server/cloudflare.py
uif_server/server_main.py_bak
uif_server/test_uif_server.py
uif_server/test_uif_server.py~
uif_server/uif_server.py
uif_server/uif_server.py~
abcd_0329-1645514386.dist-info/METADATA
abcd_0329-1645514386.dist-info/WHEEL
abcd_0329-1645514386.dist-info/top_level.txt
abcd_0329-1645514386.dist-info/RECORD
